{
    "id": "asgard-angle-head-adapter-cfa-ad-sch",
    "title": "CFA-AD_SCH",
    "product_name": "Angle Head Adapter",
    "sku": "CFA-AD",
    "diagramPages": [
        1
    ],
    "legendPages": [],
    "parts": [
        {
            "id": "402033",
            "name": "402033 Ball Coupling - Threaded Angle Head Ball",
            "quantity": 1,
            "sku": "",
            "source_sku": "4814"
        },
        {
            "id": "883024",
            "name": "883024",
            "quantity": 1,
            "sku": ""
        },
        {
            "id": "883021",
            "name": "NS Adapter Jam Nut",
            "quantity": 1,
            "sku": "",
            "source_sku": "883021"
        }
    ],
    "coordinates": {
        "402033": {
            "id": "402033",
            "x_px": null,
            "y_px": null,
            "x_pct": 54.75,
            "y_pct": 16.299999999999997,
            "shape": "rectangle",
            "pageNumber": 1,
            "rotation": 0
        },
        "883021": {
            "id": "883021",
            "x_px": null,
            "y_px": null,
            "x_pct": 38.699999999999996,
            "y_pct": 91,
            "shape": "rectangle",
            "pageNumber": 1,
            "rotation": 0
        },
        "883024": {
            "id": "883024",
            "x_px": null,
            "y_px": null,
            "x_pct": 36.5,
            "y_pct": 34.150000000000006,
            "shape": "rectangle",
            "pageNumber": 1,
            "rotation": 0
        }
    },
    "schema_version": "1.0",
    "image_natural_width": 1376,
    "image_natural_height": 768
}
