{
    "id": "columbia-angle-head-sch",
    "title": "columbia-angle-head-sch-schematic-page-01.webp",
    "diagramPages": [
        1
    ],
    "legendPages": [],
    "parts": [
        {
            "id": "FA 235",
            "name": "6-32 x 1/8 Set Screw (FA235)",
            "quantity": 1,
            "sku": "FA235"
        },
        {
            "id": "AH 6",
            "name": "Funnel Retainer Spring (AH6)",
            "quantity": 1,
            "sku": "AH-6"
        },
        {
            "id": "AH 7-2.5\"",
            "name": "Frame Tension Spring 2-1/2 in (AH7-2.5)",
            "quantity": 1,
            "sku": "AH7-2.5"
        },
        {
            "id": "AH 7-3\"",
            "name": "Angle Head Frame Tension Spring (AH7-3)",
            "quantity": 1,
            "sku": "AH7-3"
        },
        {
            "id": "FA 235",
            "name": "6-32 x 1/8 Set Screw (FA235)",
            "quantity": 1,
            "sku": "FA235"
        },
        {
            "id": "FA 235",
            "name": "6-32 x 1/8 Set Screw (FA235)",
            "quantity": 1,
            "sku": "FA235"
        },
        {
            "id": "AH 3-3\"",
            "name": "3\" Angle Head Carbide Blade (AH33)",
            "quantity": 1,
            "sku": "AH3-3"
        },
        {
            "id": "FA 239",
            "name": "6-32 x ¼\" Binder Slot (FA239)",
            "quantity": 1,
            "sku": "FA239"
        },
        {
            "id": "AH 18",
            "name": "Socket Wear Cup (AH18)",
            "quantity": 1,
            "sku": "AH18"
        },
        {
            "id": "AH 3-3\"",
            "name": "3\" Angle Head Carbide Blade (AH33)",
            "quantity": 1,
            "sku": "AH3-3"
        },
        {
            "id": "AH 16",
            "name": "Retaining Spring Backer (AH16)",
            "quantity": 1,
            "sku": "AH-16"
        },
        {
            "id": "FA 245",
            "name": "6-32 X 1/2\" Fill. Head Screw (FA245)",
            "quantity": 1,
            "sku": "FA245"
        },
        {
            "id": "FA 236",
            "name": "6-32 x 1/8\" Binder Slot (FA236)",
            "quantity": 1,
            "sku": "FA236"
        },
        {
            "id": "AH 5",
            "name": "Frame Retainer Clip (AH5)",
            "quantity": 1,
            "sku": "AH5"
        },
        {
            "id": "AH 4",
            "name": "Angle Head Side Blade (AH4)",
            "quantity": 1,
            "sku": "AH4"
        },
        {
            "id": "AH 2-3\" L",
            "name": "Left Frame Sub-Assembly 3 in (AHA2-3L)",
            "quantity": 1,
            "sku": "AH-23"
        },
        {
            "id": "AH 8",
            "name": "Retainer Clip (Short)",
            "quantity": 1,
            "sku": "AH8"
        },
        {
            "id": "AH 9",
            "name": "Retainer Clip (Long)",
            "quantity": 1,
            "sku": "AH9"
        },
        {
            "id": "FA 258",
            "name": "8-32 x ¼\" Half Dog Set (FA258)",
            "quantity": 1,
            "sku": "FA258"
        },
        {
            "id": "AH 1",
            "name": "Spring Housing Angle Head (AH1A)",
            "quantity": 1,
            "sku": "AH1A"
        },
        {
            "id": "AH 2-3\" R",
            "name": "Right Frame Sub-Assembly 3 in (AHA2-3R)",
            "quantity": 1,
            "sku": "AH-23"
        },
        {
            "id": "AH 4",
            "name": "Angle Head Side Blade (AH4)",
            "quantity": 1,
            "sku": "AH4"
        },
        {
            "id": "FA 221",
            "name": "#6 Belleville Washer (FA221)",
            "quantity": 1,
            "sku": "FA221"
        },
        {
            "id": "AH 11",
            "name": "Return Spring Post Angle Head (AH11)",
            "quantity": 1,
            "sku": "AH-11"
        },
        {
            "id": "FA 221",
            "name": "#6 Belleville Washer (FA221)",
            "quantity": 1,
            "sku": "FA221"
        },
        {
            "id": "AH 12",
            "name": "Head Casting 2 in (AH1-2)",
            "quantity": 1,
            "sku": "AH1-2"
        },
        {
            "id": "FA 210",
            "name": "4/40 x 3/16\"  Binder Slot (FA210)",
            "quantity": 1,
            "sku": "FA210"
        },
        {
            "id": "AH 1-3.5\"",
            "name": "Head Casting 3-1/2 in (AH1-3.5)",
            "quantity": 1,
            "sku": "AH1-3.5"
        },
        {
            "id": "AH 23",
            "name": "Angle Head Frame Retaining Pin (AH23)",
            "quantity": 1,
            "sku": "AH-23"
        },
        {
            "id": "FA 228",
            "name": "#6 Flat Washer (FA228)",
            "quantity": 1,
            "sku": "FA228"
        },
        {
            "id": "AH 21",
            "name": "Angle Head Hinge Spacer (AH21)",
            "quantity": 1,
            "sku": "AH-21"
        },
        {
            "id": "AH 20",
            "name": "Angle Head Pivot Pin (AH20)",
            "quantity": 1,
            "sku": "AH-20"
        },
        {
            "id": "AH 22",
            "name": "Angle Head Frame Clamp (AH22)",
            "quantity": 1,
            "sku": "AH-22"
        },
        {
            "id": "AH 1",
            "name": "Spring Housing Angle Head (AH1A)",
            "quantity": 1,
            "sku": "AH1A"
        }
    ],
    "coordinates": {
        "FA 235": {
            "id": "FA 235",
            "x_px": null,
            "y_px": null,
            "x_pct": 15.423341111273153,
            "y_pct": 26.849990233993513,
            "shape": "rectangle",
            "pageNumber": 1,
            "rotation": 0
        },
        "AH 6": {
            "id": "AH 6",
            "x_px": null,
            "y_px": null,
            "x_pct": 44.54662388799767,
            "y_pct": 11.849990233993516,
            "shape": "rectangle",
            "pageNumber": 1,
            "rotation": 0
        },
        "AH 7-2.5\"": {
            "id": "AH 7-2.5\"",
            "x_px": null,
            "y_px": null,
            "x_pct": 50.23329444363424,
            "y_pct": 14.100078128051877,
            "shape": "rectangle",
            "pageNumber": 1,
            "rotation": 0
        },
        "AH 7-3\"": {
            "id": "AH 7-3\"",
            "x_px": null,
            "y_px": null,
            "x_pct": 55.93667055563657,
            "y_pct": 14.100078128051877,
            "shape": "rectangle",
            "pageNumber": 1,
            "rotation": 0
        },
        "AH 3-3\"": {
            "id": "AH 3-3\"",
            "x_px": null,
            "y_px": null,
            "x_pct": 50.33998833309027,
            "y_pct": 37.4,
            "shape": "rectangle",
            "pageNumber": 1,
            "rotation": 0
        },
        "FA 239": {
            "id": "FA 239",
            "x_px": null,
            "y_px": null,
            "x_pct": 31.5,
            "y_pct": 37.400000000000006,
            "shape": "rectangle",
            "pageNumber": 1,
            "rotation": 0
        },
        "AH 18": {
            "id": "AH 18",
            "x_px": null,
            "y_px": null,
            "x_pct": 45.099999999999994,
            "y_pct": 37.400000000000006,
            "shape": "rectangle",
            "pageNumber": 1,
            "rotation": 0
        },
        "AH 16": {
            "id": "AH 16",
            "x_px": null,
            "y_px": null,
            "x_pct": 25.500000000000004,
            "y_pct": 44.599999999999994,
            "shape": "rectangle",
            "pageNumber": 1,
            "rotation": 0
        },
        "FA 245": {
            "id": "FA 245",
            "x_px": null,
            "y_px": null,
            "x_pct": 44.72665888872685,
            "y_pct": 45.94998046798703,
            "shape": "rectangle",
            "pageNumber": 1,
            "rotation": 0
        },
        "FA 236": {
            "id": "FA 236",
            "x_px": null,
            "y_px": null,
            "x_pct": 18.7,
            "y_pct": 54.599999999999994,
            "shape": "rectangle",
            "pageNumber": 1,
            "rotation": 0
        },
        "AH 5": {
            "id": "AH 5",
            "x_px": null,
            "y_px": null,
            "x_pct": 56,
            "y_pct": 54.599999999999994,
            "shape": "rectangle",
            "pageNumber": 1,
            "rotation": 0
        },
        "AH 4": {
            "id": "AH 4",
            "x_px": null,
            "y_px": null,
            "x_pct": 67.19999999999999,
            "y_pct": 73.55,
            "shape": "rectangle",
            "pageNumber": 1,
            "rotation": 0
        },
        "AH 2-3\" L": {
            "id": "AH 2-3\" L",
            "x_px": null,
            "y_px": null,
            "x_pct": 9.9,
            "y_pct": 73.29999023399351,
            "shape": "rectangle",
            "pageNumber": 1,
            "rotation": 0
        },
        "AH 8": {
            "id": "AH 8",
            "x_px": null,
            "y_px": null,
            "x_pct": 24.950000000000003,
            "y_pct": 80.75,
            "shape": "rectangle",
            "pageNumber": 1,
            "rotation": 0
        },
        "AH 9": {
            "id": "AH 9",
            "x_px": null,
            "y_px": null,
            "x_pct": 30.9,
            "y_pct": 80.75,
            "shape": "rectangle",
            "pageNumber": 1,
            "rotation": 0
        },
        "FA 258": {
            "id": "FA 258",
            "x_px": null,
            "y_px": null,
            "x_pct": 45.099999999999994,
            "y_pct": 80.75,
            "shape": "rectangle",
            "pageNumber": 1,
            "rotation": 0
        },
        "AH 1": {
            "id": "AH 1",
            "x_px": null,
            "y_px": null,
            "x_pct": 94.80000000000001,
            "y_pct": 82.25,
            "shape": "rectangle",
            "pageNumber": 1,
            "rotation": 0
        },
        "AH 2-3\" R": {
            "id": "AH 2-3\" R",
            "x_px": null,
            "y_px": null,
            "x_pct": 59.036670555636576,
            "y_pct": 73.29999023399351,
            "shape": "rectangle",
            "pageNumber": 1,
            "rotation": 0
        },
        "FA 221": {
            "id": "FA 221",
            "x_px": null,
            "y_px": null,
            "x_pct": 91.4,
            "y_pct": 30.5,
            "shape": "rectangle",
            "pageNumber": 1,
            "rotation": 0
        },
        "AH 11": {
            "id": "AH 11",
            "x_px": null,
            "y_px": null,
            "x_pct": 87.87334111127315,
            "y_pct": 17.5,
            "shape": "rectangle",
            "pageNumber": 1,
            "rotation": 0
        },
        "AH 12": {
            "id": "AH 12",
            "x_px": null,
            "y_px": null,
            "x_pct": 91.30000000000001,
            "y_pct": 39.5,
            "shape": "rectangle",
            "pageNumber": 1,
            "rotation": 0
        },
        "FA 210": {
            "id": "FA 210",
            "x_px": null,
            "y_px": null,
            "x_pct": 78.91332944436343,
            "y_pct": 47.59993163795461,
            "shape": "rectangle",
            "pageNumber": 1,
            "rotation": 0
        },
        "AH 1-3.5\"": {
            "id": "AH 1-3.5\"",
            "x_px": null,
            "y_px": null,
            "x_pct": 91.33672889018521,
            "y_pct": 48.34996093597405,
            "shape": "rectangle",
            "pageNumber": 1,
            "rotation": 0
        },
        "AH 23": {
            "id": "AH 23",
            "x_px": null,
            "y_px": null,
            "x_pct": 74.9,
            "y_pct": 82.25,
            "shape": "rectangle",
            "pageNumber": 1,
            "rotation": 0
        },
        "FA 228": {
            "id": "FA 228",
            "x_px": null,
            "y_px": null,
            "x_pct": 78.65,
            "y_pct": 82.25,
            "shape": "rectangle",
            "pageNumber": 1,
            "rotation": 0
        },
        "AH 21": {
            "id": "AH 21",
            "x_px": null,
            "y_px": null,
            "x_pct": 82.7,
            "y_pct": 82.25,
            "shape": "rectangle",
            "pageNumber": 1,
            "rotation": 0
        },
        "AH 20": {
            "id": "AH 20",
            "x_px": null,
            "y_px": null,
            "x_pct": 86.7,
            "y_pct": 82.25,
            "shape": "rectangle",
            "pageNumber": 1,
            "rotation": 0
        },
        "AH 22": {
            "id": "AH 22",
            "x_px": null,
            "y_px": null,
            "x_pct": 90.7,
            "y_pct": 82.25,
            "shape": "rectangle",
            "pageNumber": 1,
            "rotation": 0
        }
    },
    "schema_version": "1.0",
    "image_natural_width": 2400,
    "image_natural_height": 1792
}
